<?xml version='1.0' encoding='UTF-8'?>
<incidents xmlns:xsi='http://www.w3.org/2001/XMLSchema-instance' xsi:noNamespaceSchemaLocation='http://www.gstatic.com/road-incidents/incidents_feed.xsd'>
<incident id='FDFROZZ'>
<creationtime>2017-11-17T23:26:30-03:00</creationtime>
<type>ACCIDENT</type>
<subtype>ACCIDENT_MINOR</subtype>
 <description>U</description>
<location>
<polyline>-346357383 -587861602</polyline>
</location>
 <starttime>2017-11-17T23:25:54-03:00</starttime>
</incident>
</incidents>
